CHANGES.txt
COPYRIGHT.txt
LICENSE.txt
README.txt
bootstrap.py
buildout.cfg
setup.py
src/zc/__init__.py
src/zc.datetimewidget.egg-info/PKG-INFO
src/zc.datetimewidget.egg-info/SOURCES.txt
src/zc.datetimewidget.egg-info/dependency_links.txt
src/zc.datetimewidget.egg-info/namespace_packages.txt
src/zc.datetimewidget.egg-info/not-zip-safe
src/zc.datetimewidget.egg-info/requires.txt
src/zc.datetimewidget.egg-info/top_level.txt
src/zc/datetimewidget/TODO.txt
src/zc/datetimewidget/__init__.py
src/zc/datetimewidget/configure.zcml
src/zc/datetimewidget/datetimewidget.py
src/zc/datetimewidget/datetimewidget.txt
src/zc/datetimewidget/ftesting.zcml
src/zc/datetimewidget/overrides.zcml
src/zc/datetimewidget/tests.py
src/zc/datetimewidget/widgets.txt
src/zc/datetimewidget/demo/README.txt
src/zc/datetimewidget/demo/__init__.py
src/zc/datetimewidget/demo/configure.zcml
src/zc/datetimewidget/demo/content.py
src/zc/datetimewidget/demo/interfaces.py
src/zc/datetimewidget/demo/tests.py
src/zc/datetimewidget/demo/timezone.py
src/zc/datetimewidget/resources/calendar-blue.css
src/zc/datetimewidget/resources/calendar-blue2.css
src/zc/datetimewidget/resources/calendar-brown.css
src/zc/datetimewidget/resources/calendar-green.css
src/zc/datetimewidget/resources/calendar-setup.js
src/zc/datetimewidget/resources/calendar-system.css
src/zc/datetimewidget/resources/calendar-tas.css
src/zc/datetimewidget/resources/calendar-win2k-1.css
src/zc/datetimewidget/resources/calendar-win2k-2.css
src/zc/datetimewidget/resources/calendar-win2k-cold-1.css
src/zc/datetimewidget/resources/calendar-win2k-cold-2.css
src/zc/datetimewidget/resources/calendar.js
src/zc/datetimewidget/resources/datetimewidget.js
src/zc/datetimewidget/resources/fix_up_css.sh
src/zc/datetimewidget/resources/img.gif
src/zc/datetimewidget/resources/menuarrow.gif
src/zc/datetimewidget/resources/menuarrow2.gif
src/zc/datetimewidget/resources/languages/calendar-al.js
src/zc/datetimewidget/resources/languages/calendar-bg.js
src/zc/datetimewidget/resources/languages/calendar-big5.js
src/zc/datetimewidget/resources/languages/calendar-br.js
src/zc/datetimewidget/resources/languages/calendar-ca.js
src/zc/datetimewidget/resources/languages/calendar-cs-win.js
src/zc/datetimewidget/resources/languages/calendar-da.js
